gitea_auto_update/__init__.py
gitea_auto_update/update.py
gitea_auto_update/lib/__init__.py
gitea_auto_update/lib/build.py
gitea_auto_update/lib/download.py
gitea_auto_update/lib/test_version.py
gitea_auto_update/lib/version.py
gitea_auto_update-2.0.13.dist-info/LICENSE
gitea_auto_update-2.0.13.dist-info/METADATA
gitea_auto_update-2.0.13.dist-info/WHEEL
gitea_auto_update-2.0.13.dist-info/entry_points.txt
gitea_auto_update-2.0.13.dist-info/top_level.txt
gitea_auto_update-2.0.13.dist-info/RECORD
