Metadata-Version: 2.1
Name: gitea_auto_update
Version: 2.0.13
Summary: A script which can update gitea to a new version.
Home-page: https://github.com/CMiksche/gitea-auto-update
Author: Christoph Miksche
Author-email: autoupdate@chapati.systems
License: GPLv3
Keywords: gitea,update,debian,linux
Classifier: Programming Language :: Python :: 3
Classifier: License :: OSI Approved :: GNU General Public License v3 or later (GPLv3+)
Classifier: Operating System :: Unix
Requires-Python: >=3
License-File: LICENSE
Requires-Dist: requests
Requires-Dist: packaging
Requires-Dist: fire
Requires-Dist: configparser
